good/__init__.py
good/helpers.py
good/voluptuous.py
good/schema/__init__.py
good/schema/compiler.py
good/schema/errors.py
good/schema/markers.py
good/schema/signals.py
good/schema/util.py
good/validators/__init__.py
good/validators/base.py
good/validators/boolean.py
good/validators/dates.py
good/validators/files.py
good/validators/numbers.py
good/validators/predicates.py
good/validators/strings.py
good/validators/types.py
good/validators/values.py
good-0.0.8.dist-info/LICENSE
good-0.0.8.dist-info/METADATA
good-0.0.8.dist-info/WHEEL
good-0.0.8.dist-info/top_level.txt
good-0.0.8.dist-info/RECORD
