Metadata-Version: 2.1
Name: good
Version: 0.0.8
Summary: Slim yet handsome validation library 
Home-page: https://github.com/kolypto/py-good
Author: Mark Vartanyan
Author-email: kolypto@gmail.com
License: BSD
Keywords: validation
Platform: any
Classifier: Development Status :: 5 - Production/Stable
Classifier: Intended Audience :: Developers
Classifier: Natural Language :: English
Classifier: Operating System :: OS Independent
Classifier: Programming Language :: Python :: 2
Classifier: Programming Language :: Python :: 3
Classifier: Topic :: Software Development :: Libraries :: Python Modules
